zmqruntime/__init__.py
zmqruntime/ack_listener.py
zmqruntime/client.py
zmqruntime/config.py
zmqruntime/messages.py
zmqruntime/queue_tracker.py
zmqruntime/runner.py
zmqruntime/server.py
zmqruntime/transport.py
zmqruntime/viewer_state.py
zmqruntime/execution/__init__.py
zmqruntime/execution/client.py
zmqruntime/execution/server.py
zmqruntime/streaming/__init__.py
zmqruntime/streaming/process_manager.py
zmqruntime/streaming/server.py
zmqruntime-0.1.3.dist-info/METADATA
zmqruntime-0.1.3.dist-info/WHEEL
zmqruntime-0.1.3.dist-info/licenses/LICENSE
zmqruntime-0.1.3.dist-info/RECORD
