Metadata-Version: 2.4
Name: zmqruntime
Version: 0.1.3
Summary: Generic ZMQ-based distributed execution framework
Project-URL: Homepage, https://github.com/OpenHCSDev/zmqruntime
Project-URL: Documentation, https://github.com/OpenHCSDev/zmqruntime#readme
Project-URL: Repository, https://github.com/OpenHCSDev/zmqruntime
Project-URL: Issues, https://github.com/OpenHCSDev/zmqruntime/issues
Author-email: Tristan Simas <tristan.simas@mail.mcgill.ca>
License: MIT
License-File: LICENSE
Keywords: distributed,execution,messaging,rpc,zeromq,zmq
Classifier: Development Status :: 4 - Beta
Classifier: Intended Audience :: Developers
Classifier: License :: OSI Approved :: MIT License
Classifier: Programming Language :: Python :: 3
Classifier: Programming Language :: Python :: 3.10
Classifier: Programming Language :: Python :: 3.11
Classifier: Programming Language :: Python :: 3.12
Classifier: Programming Language :: Python :: 3.13
Classifier: Topic :: Software Development :: Libraries :: Python Modules
Classifier: Topic :: System :: Distributed Computing
Requires-Python: >=3.10
Requires-Dist: pyzmq>=22.0
Provides-Extra: dev
Requires-Dist: black>=23.0; extra == 'dev'
Requires-Dist: pytest-cov>=4.0; extra == 'dev'
Requires-Dist: pytest>=7.0; extra == 'dev'
Requires-Dist: ruff>=0.1.0; extra == 'dev'
Provides-Extra: registry
Requires-Dist: metaclass-registry; extra == 'registry'
